ibkr_mcp/__init__.cpython-313-darwin.so
ibkr_mcp/__main__.cpython-313-darwin.so
ibkr_mcp/server.cpython-313-darwin.so
ibkr_mcp/core/__init__.cpython-313-darwin.so
ibkr_mcp/core/auth.cpython-313-darwin.so
ibkr_mcp/core/greeks.cpython-313-darwin.so
ibkr_mcp/core/market_state.cpython-313-darwin.so
ibkr_mcp/core/option_data.cpython-313-darwin.so
ibkr_mcp/core/playbooks.cpython-313-darwin.so
ibkr_mcp/core/positions.cpython-313-darwin.so
ibkr_mcp/core/rules.cpython-313-darwin.so
ibkr_mcp/core/stock_data.cpython-313-darwin.so
ibkr_mcp/core/technical_indicators.cpython-313-darwin.so
ibkr_mcp/database/__init__.cpython-313-darwin.so
ibkr_mcp/database/manager.cpython-313-darwin.so
ibkr_mcp/database/models.cpython-313-darwin.so
ibkr_mcp/database/repositories.cpython-313-darwin.so
ibkr_mcp/mcp/__init__.cpython-313-darwin.so
ibkr_mcp/mcp/resources.cpython-313-darwin.so
ibkr_mcp/mcp/tools.cpython-313-darwin.so
ibkr_mcp/services/__init__.cpython-313-darwin.so
ibkr_mcp/services/base.cpython-313-darwin.so
ibkr_mcp/services/data_enrichment.cpython-313-darwin.so
ibkr_mcp/services/market_data.cpython-313-darwin.so
ibkr_mcp/services/news_service.cpython-313-darwin.so
ibkr_mcp/services/option_chain.cpython-313-darwin.so
ibkr_mcp/services/portfolio.cpython-313-darwin.so
ibkr_mcp/services/risk_service.cpython-313-darwin.so
ibkr_mcp/services/stock_data.cpython-313-darwin.so
ibkr_mcp/services/strategy_analysis.cpython-313-darwin.so
ibkr_mcp/services/strategy_factory.cpython-313-darwin.so
ibkr_mcp/services/trade.cpython-313-darwin.so
ibkr_mcp/strategies/__init__.cpython-313-darwin.so
ibkr_mcp/strategies/base.cpython-313-darwin.so
ibkr_mcp/strategies/strategy_covered_call.cpython-313-darwin.so
ibkr_mcp/strategies/strategy_iron_condor.cpython-313-darwin.so
ibkr_mcp/strategies/strategy_pmcc.cpython-313-darwin.so
ibkr_mcp/strategies/strategy_put_credit_spread.cpython-313-darwin.so
ibkr_mcp/strategies/strategy_vertical_spread.cpython-313-darwin.so
ibkr_mcp-0.2.5.dist-info/licenses/LICENSE
ibkr_mcp-0.2.5.dist-info/METADATA
ibkr_mcp-0.2.5.dist-info/WHEEL
ibkr_mcp-0.2.5.dist-info/entry_points.txt
ibkr_mcp-0.2.5.dist-info/top_level.txt
ibkr_mcp-0.2.5.dist-info/RECORD
