Metadata-Version: 2.4
Name: ibkr-mcp
Version: 0.2.5
Summary: Interactive Brokers MCP Server for AI-powered trading
License-Expression: LicenseRef-Proprietary
Requires-Python: >=3.12
License-File: LICENSE
Requires-Dist: ib-async>=2.0.1
Requires-Dist: loguru>=0.7.3
Requires-Dist: mcp[cli]>=1.21.2
Requires-Dist: numpy>=2.3.5
Requires-Dist: pandas>=2.3.3
Requires-Dist: plotly>=6.5.0
Requires-Dist: pyarrow>=22.0.0
Requires-Dist: python-dotenv>=1.2.1
Requires-Dist: pyyaml>=6.0.3
Requires-Dist: sqlalchemy>=2.0.0
Requires-Dist: aiosqlite>=0.20.0
Requires-Dist: alembic>=1.17.2
Requires-Dist: greenlet>=3.3.0
Requires-Dist: nautilus-trader>=1.222.0
Provides-Extra: cython
Requires-Dist: cython>=3.0; extra == "cython"
Dynamic: license-file
